setup.py
gg_distributions/Binomialdistribution.py
gg_distributions/Gaussiandistribution.py
gg_distributions/Generaldistribution.py
gg_distributions/__init__.py
gg_distributions.egg-info/PKG-INFO
gg_distributions.egg-info/SOURCES.txt
gg_distributions.egg-info/dependency_links.txt
gg_distributions.egg-info/not-zip-safe
gg_distributions.egg-info/top_level.txt